py_shakespeare/__init__.py
py_shakespeare/py_shakespeare.py
py_shakespeare-0.1.0.dist-info/LICENSE
py_shakespeare-0.1.0.dist-info/WHEEL
py_shakespeare-0.1.0.dist-info/METADATA
py_shakespeare-0.1.0.dist-info/RECORD
