Metadata-Version: 2.1
Name: py-shakespeare
Version: 0.1.0
Summary: Python package to obtain Shakespeare script and monologue
License: MIT
Author: Hamidah Alatas
Requires-Python: >=3.9,<4.0
Classifier: License :: OSI Approved :: MIT License
Classifier: Programming Language :: Python :: 3
Classifier: Programming Language :: Python :: 3.9
Requires-Dist: bs4 (>=0.0.1,<0.0.2)
Requires-Dist: lxml (>=4.7.1,<5.0.0)
Requires-Dist: nltk (>=3.6.5,<4.0.0)
Requires-Dist: pandas (>=1.3.5,<2.0.0)
Requires-Dist: requests (>=2.26.0,<3.0.0)
Requires-Dist: simplejson (>=3.17.6,<4.0.0)
Requires-Dist: textstat (>=0.7.2,<0.8.0)
